{
  "parent": "minecraft:recipes/root",
  "criteria": {
    "has_pod_emerald": {
      "conditions": {
        "items": [
          {
            "items": "treeminer:pod_emerald"
          }
        ]
      },
      "trigger": "minecraft:inventory_changed"
    },
    "has_the_recipe": {
      "conditions": {
        "recipe": "treeminer:pod_emerald_to_cooked_pod_emerald_furnace"
      },
      "trigger": "minecraft:recipe_unlocked"
    }
  },
  "requirements": [
    [
      "has_the_recipe",
      "has_pod_emerald"
    ]
  ],
  "rewards": {
    "recipes": [
      "treeminer:pod_emerald_to_cooked_pod_emerald_furnace"
    ]
  }
}